omglib/__init__.py
omglib/advx/__init__.py
omglib/advx/advlist.py
omglib/ai/__init__.py
omglib/ai/imap.py
omglib/ai/map.py
omglib/ai/tts.py
omglib/ai/variables.py
omglib/event/__init__.py
omglib/event/events.py
omglib/llm/__init__.py
omglib/llm/platforms.py
omglib/llm/requirements.txt
omglib/llm/test_api.py
omglib/llm/tool_test.py
omglib/llm/tools.py
omglib/llm/tools_base.py
omglib/llm/beta/__init__.py
omglib/llm/beta/workers/__init__.py
omglib/llm/beta/workers/wmap.py
omglib/llm/beta/workers/wmodels.py
omglib/selector/__init__.py
omglib/selector/selector.py
omglib/tools/__init__.py
omglib/tools/fastbit.py
omglib/tools/pathtools.py
omglib/tools/ziptools.py
omglib/tools/dicttools/__init__.py
omglib/tools/dicttools/perfectdict.py
omglib/tools/listtools/__init__.py
omglib/tools/listtools/listing.py
omglib-0.1.44.dist-info/LICENSE
omglib-0.1.44.dist-info/METADATA
omglib-0.1.44.dist-info/WHEEL
omglib-0.1.44.dist-info/top_level.txt
omglib-0.1.44.dist-info/RECORD
