Metadata-Version: 2.2
Name: omglib
Version: 0.1.44
Summary: OMEGAPy Python Toolkit all projects need
Author-email: M1778 <m1778.pc@gmail.com>
Maintainer-email: M1778 <m1778.pc@gmail.com>
License:                     GNU GENERAL PUBLIC LICENSE
Project-URL: Documentation, https://pypi.org/project/omglib/
Project-URL: Repository, https://github.com/M1778M/omglib
Project-URL: Issues, https://github.com/M1778M/omglib/issues
Keywords: omg,omglib,M1778,OMEGAPy,omegapy,omglibrary
Classifier: Development Status :: 3 - Alpha
Classifier: Intended Audience :: Developers
Classifier: Topic :: Software Development :: Libraries :: Python Modules
Classifier: License :: OSI Approved :: GNU General Public License v3 (GPLv3)
Classifier: Programming Language :: Python :: 3
Classifier: Programming Language :: Python :: 3.9
Classifier: Programming Language :: Python :: 3.10
Classifier: Programming Language :: Python :: 3.11
Requires-Python: >=3.9
License-File: LICENSE
Requires-Dist: openai~=1.52.2
Requires-Dist: vosk
Requires-Dist: SpeechRecognition
Requires-Dist: pyaudio>0.2.13
Requires-Dist: pydub
Requires-Dist: openai-whisper
Requires-Dist: pySmartDL==1.3.4
